[
  {
    "title": "Titanic",
    "year": 1997
  },
  {
    "title": "Star Wars: Episode I - The Phantom Menace",
    "year": 1999
  },
  {
    "title": "Jurassic Park",
    "year": 1993
  },
  {
    "title": "The Lion King",
    "year": 1994
  },
  {
    "title": "The Sixth Sense",
    "year": 1999
  },
  {
    "title": "Independence Day",
    "year": 1996
  },
  {
    "title": "Home Alone",
    "year": 1990
  },
  {
    "title": "Men in Black",
    "year": 1997
  },
  {
    "title": "Toy Story 2",
    "year": 1999
  },
  {
    "title": "Ghost",
    "year": 1990
  },
  {
    "title": "The Matrix",
    "year": 1999
  },
  {
    "title": "Twister",
    "year": 1996
  },
  {
    "title": "Toy Story",
    "year": 1995
  },
  {
    "title": "Armageddon",
    "year": 1998
  },
  {
    "title": "Beauty and the Beast",
    "year": 1991
  },
  {
    "title": "Terminator 2: Judgment Day",
    "year": 1991
  },
  {
    "title": "A Bug's Life",
    "year": 1998
  },
  {
    "title": "The Mummy",
    "year": 1999
  },
  {
    "title": "The Fugitive",
    "year": 1993
  },
  {
    "title": "Lethal Weapon 3",
    "year": 1992
  },
  {
    "title": "The Mask",
    "year": 1994
  },
  {
    "title": "Speed",
    "year": 1994
  },
  {
    "title": "Die Hard: With a Vengeance",
    "year": 1995
  },
  {
    "title": "Batman Returns",
    "year": 1992
  },
  {
    "title": "True Lies",
    "year": 1994
  },
  {
    "title": "The Rock",
    "year": 1996
  },
  {
    "title": "Dances with Wolves",
    "year": 1990
  },
  {
    "title": "Mission: Impossible",
    "year": 1996
  },
  {
    "title": "Robin Hood: Prince of Thieves",
    "year": 1991
  },
  {
    "title": "The Bodyguard",
    "year": 1992
  },
  {
    "title": "The Santa Clause",
    "year": 1994
  },
  {
    "title": "The Prince of Egypt",
    "year": 1998
  },
  {
    "title": "Waterworld",
    "year": 1995
  },
  {
    "title": "The Hunt for Red October",
    "year": 1990
  },
  {
    "title": "The Firm",
    "year": 1993
  },
  {
    "title": "101 Dalmatians",
    "year": 1996
  },
  {
    "title": "Sister Act",
    "year": 1992
  },
  {
    "title": "The Birdcage",
    "year": 1996
  },
  {
    "title": "The Hand That Rocks the Cradle",
    "year": 1992
  },
  {
    "title": "The Pelican Brief",
    "year": 1993
  },
  {
    "title": "The Nutty Professor",
    "year": 1996
  },
  {
    "title": "The Green Mile",
    "year": 1999
  },
  {
    "title": "My Best Friend's Wedding",
    "year": 1997
  },
  {
    "title": "The Parent Trap",
    "year": 1998
  },
  {
    "title": "Runaway Bride",
    "year": 1999
  },
  {
    "title": "The Wedding Singer",
    "year": 1998
  },
  {
    "title": "You've Got Mail",
    "year": 1998
  },
  {
    "title": "Sleepless in Seattle",
    "year": 1993
  },
  {
    "title": "Pretty Woman",
    "year": 1990
  },
  {
    "title": "Father of the Bride",
    "year": 1991
  },
  {
    "title": "Father of the Bride Part II",
    "year": 1995
  },
  {
    "title": "While You Were Sleeping",
    "year": 1995
  },
  {
    "title": "The First Wives Club",
    "year": 1996
  },
  {
    "title": "Stepmom",
    "year": 1998
  },
  {
    "title": "The American President",
    "year": 1995
  },
  {
    "title": "City Slickers",
    "year": 1991
  },
  {
    "title": "Grumpy Old Men",
    "year": 1993
  },
  {
    "title": "Grumpier Old Men",
    "year": 1995
  },
  {
    "title": "The Birdcage",
    "year": 1996
  },
  {
    "title": "Analyze This",
    "year": 1999
  },
  {
    "title": "As Good as It Gets",
    "year": 1997
  },
  {
    "title": "Liar Liar",
    "year": 1997
  },
  {
    "title": "The Cable Guy",
    "year": 1996
  },
  {
    "title": "The Waterboy",
    "year": 1998
  },
  {
    "title": "Big Daddy",
    "year": 1999
  },
  {
    "title": "The Wedding Singer",
    "year": 1998
  },
  {
    "title": "The Nutty Professor",
    "year": 1996
  },
  {
    "title": "A Goofy Movie",
    "year": 1995
  }
]